bam_readgroup_to_json/__init__.py
bam_readgroup_to_json/__main__.py
bam_readgroup_to_json/main.py
bam_readgroup_to_json-0.26.dist-info/LICENSE
bam_readgroup_to_json-0.26.dist-info/METADATA
bam_readgroup_to_json-0.26.dist-info/WHEEL
bam_readgroup_to_json-0.26.dist-info/entry_points.txt
bam_readgroup_to_json-0.26.dist-info/top_level.txt
bam_readgroup_to_json-0.26.dist-info/RECORD
