Metadata-Version: 2.1
Name: bam-readgroup-to-json
Version: 0.26
Summary: convert each readgroup id to a json file from a BAM
Home-page: https://github.com/jeremiahsavage/bam_readgroup_to_json/
Author: Jeremiah H. Savage
Author-email: jeremiahsavage@gmail.com
License: Apache 2.0
Platform: UNKNOWN
Classifier: Development Status :: 3 - Alpha
Classifier: Intended Audience :: Developers
Classifier: License :: OSI Approved :: Apache Software License
Classifier: Programming Language :: Python
Classifier: Programming Language :: Python :: 2
Classifier: Programming Language :: Python :: 3
Requires-Dist: pandas
Requires-Dist: pysam
Requires-Dist: sqlalchemy
